odoo/addons/web_responsive_company/README.rst
odoo/addons/web_responsive_company/__init__.py
odoo/addons/web_responsive_company/__manifest__.py
odoo/addons/web_responsive_company/demo/res_company.xml
odoo/addons/web_responsive_company/demo/res_groups.xml
odoo/addons/web_responsive_company/i18n/fa.po
odoo/addons/web_responsive_company/i18n/fr.po
odoo/addons/web_responsive_company/i18n/web_responsive_company.pot
odoo/addons/web_responsive_company/models/__init__.py
odoo/addons/web_responsive_company/models/ir_http.py
odoo/addons/web_responsive_company/readme/CONTRIBUTORS.rst
odoo/addons/web_responsive_company/readme/DESCRIPTION.rst
odoo/addons/web_responsive_company/readme/INSTALL.rst
odoo/addons/web_responsive_company/readme/ROADMAP.rst
odoo/addons/web_responsive_company/readme/USAGE.rst
odoo/addons/web_responsive_company/static/description/company_menu.png
odoo/addons/web_responsive_company/static/description/icon.png
odoo/addons/web_responsive_company/static/description/index.html
odoo/addons/web_responsive_company/static/img/res_company-acsone.png
odoo/addons/web_responsive_company/static/img/res_company-akretion.png
odoo/addons/web_responsive_company/static/img/res_company-camp_to_camp.svg
odoo/addons/web_responsive_company/static/img/res_company-coop_it_easy.png
odoo/addons/web_responsive_company/static/img/res_company-grap.png
odoo/addons/web_responsive_company/static/img/res_company-tecnativa.svg
odoo/addons/web_responsive_company/static/src/js/web_responsive_company.js
odoo/addons/web_responsive_company/static/src/scss/web_responsive_company.scss
odoo/addons/web_responsive_company/static/src/xml/web_responsive_company.xml
odoo/addons/web_responsive_company/views/assets.xml
odoo12_addon_web_responsive_company-12.0.1.0.0.99.dev8.dist-info/METADATA
odoo12_addon_web_responsive_company-12.0.1.0.0.99.dev8.dist-info/WHEEL
odoo12_addon_web_responsive_company-12.0.1.0.0.99.dev8.dist-info/top_level.txt
odoo12_addon_web_responsive_company-12.0.1.0.0.99.dev8.dist-info/RECORD
